workcalc/__init__.py
workcalc/data/__init__.py
workcalc/data/sessions.py
workcalc/data/stats.py
workcalc/data/streaks.py
workcalc/data/summary.py
workcalc/data/time.py
workcalc/data/work_item.py
workcalc/main.py
workcalc/plugin.py
workcalc/plugins/__init__.py
workcalc/plugins/bounce.py
workcalc/plugins/git.py
workcalc-0.1.5.dist-info/METADATA
workcalc-0.1.5.dist-info/WHEEL
workcalc-0.1.5.dist-info/entry_points.txt
workcalc-0.1.5.dist-info/RECORD
