Metadata-Version: 2.3
Name: workcalc
Version: 0.1.5
Summary: Calculate how much time went into a project
Author: Danny Stewart
Author-email: danny@stewart.cc
Requires-Python: >=3.12
Classifier: Programming Language :: Python :: 3
Classifier: Programming Language :: Python :: 3.12
Classifier: Programming Language :: Python :: 3.13
Requires-Dist: dsbase (>=0.3.7,<0.4.0)
Project-URL: Repository, https://github.com/dannystewart/dsbin
